vasttrafik/__init__.py
vasttrafik/cli.py
vasttrafik_cli-1.13.dist-info/COPYING
vasttrafik_cli-1.13.dist-info/METADATA
vasttrafik_cli-1.13.dist-info/WHEEL
vasttrafik_cli-1.13.dist-info/entry_points.txt
vasttrafik_cli-1.13.dist-info/top_level.txt
vasttrafik_cli-1.13.dist-info/RECORD
