Metadata-Version: 2.1
Name: vasttrafik-cli
Version: 1.13
Summary: CLI for the public transport in Göteborg and the Västra Götaland county
Home-page: https://codeberg.org/ltworf/vasttrafik-cli
Author: Salvo 'LtWorf' Tomaselli
Author-email: tiposchi@tiscali.it
Maintainer: Salvo 'LtWorf' Tomaselli
Maintainer-email: tiposchi@tiscali.it
License: GPL3
Keywords: tram göteborg västtrafik cli
Classifier: Programming Language :: Python :: 3.11
Classifier: Programming Language :: Python :: 3.12
Classifier: Programming Language :: Python :: 3.13
Classifier: Environment :: Console
License-File: COPYING
Requires-Dist: typedload
Requires-Dist: wcwidth
Requires-Dist: xtermcolor
